gptk/__init__.py
gptk/cli.py
gptk/linalg.py
gptk/conditionals/__init__.py
gptk/conditionals/base.py
gptk/conditionals/utils.py
gptk/covariances/__init__.py
gptk/covariances/base.py
gptk/datasets/__init__.py
gptk/datasets/base.py
gptk/datasets/synthetic.py
gptk/datasets/data/jura.rda
gptk/datasets/data/motor.csv
gptk/datasets/data/snelson1d.npz
gptk/divergences/__init__.py
gptk/divergences/base.py
gptk/gpflow/__init__.py
gptk/gpflow/models/__init__.py
gptk/gpflow/models/sgpr.py
gptk/gpflow/models/svgp.py
gptk/gpflow/models/utils.py
gptk/gpflow/models/decoupled/__init__.py
gptk/gpflow/models/decoupled/base.py
gptk/gpflow/models/decoupled/odvgp.py
gptk/gpflow/models/decoupled/solvegp.py
gptk/gpflow/models/decoupled/utils.py
gptk/inducing_variables/__init__.py
gptk/inducing_variables/base.py
gptk/initializers/__init__.py
gptk/initializers/base.py
gptk/interdomain/__init__.py
gptk/interdomain/fourier.py
gptk/interdomain/spherical/__init__.py
gptk/interdomain/spherical/activated/__init__.py
gptk/metrics/__init__.py
gptk/metrics/base.py
gptk/posteriors/__init__.py
gptk/posteriors/sgpr.py
gptk/utils/__init__.py
gptk/utils/plotting.py
gp_toolkit-0.2.0.dist-info/AUTHORS.rst
gp_toolkit-0.2.0.dist-info/LICENSE
gp_toolkit-0.2.0.dist-info/METADATA
gp_toolkit-0.2.0.dist-info/WHEEL
gp_toolkit-0.2.0.dist-info/entry_points.txt
gp_toolkit-0.2.0.dist-info/top_level.txt
gp_toolkit-0.2.0.dist-info/RECORD
