Metadata-Version: 2.1
Name: gp-toolkit
Version: 0.2.0
Summary: Various extensions and mods for GPflow
Home-page: https://github.com/ltiao/gp-toolkit
Author: Louis Tiao
Author-email: louistiao@gmail.com
License: MIT license
Keywords: gptk
Classifier: Development Status :: 2 - Pre-Alpha
Classifier: Intended Audience :: Developers
Classifier: License :: OSI Approved :: MIT License
Classifier: Natural Language :: English
Classifier: Programming Language :: Python :: 3
Classifier: Programming Language :: Python :: 3.6
Classifier: Programming Language :: Python :: 3.7
Classifier: Programming Language :: Python :: 3.8
Requires-Python: >=3.6
License-File: LICENSE
License-File: AUTHORS.rst
Requires-Dist: Click (>=7.0)
Requires-Dist: rich
Requires-Dist: gpflow (<2.6.0)
Provides-Extra: datasets
Requires-Dist: scikit-learn ; extra == 'datasets'
Requires-Dist: pandas ; extra == 'datasets'
Requires-Dist: pyreadr ; extra == 'datasets'
